LICENSE
README.rst
setup.py
src/kegg_pull/__init__.py
src/kegg_pull/__main__.py
src/kegg_pull/_utils.py
src/kegg_pull/entry_ids.py
src/kegg_pull/entry_ids_cli.py
src/kegg_pull/kegg_url.py
src/kegg_pull/map.py
src/kegg_pull/map_cli.py
src/kegg_pull/pathway_organizer.py
src/kegg_pull/pathway_organizer_cli.py
src/kegg_pull/pull.py
src/kegg_pull/pull_cli.py
src/kegg_pull/rest.py
src/kegg_pull/rest_cli.py
src/kegg_pull.egg-info/PKG-INFO
src/kegg_pull.egg-info/SOURCES.txt
src/kegg_pull.egg-info/dependency_links.txt
src/kegg_pull.egg-info/entry_points.txt
src/kegg_pull.egg-info/requires.txt
src/kegg_pull.egg-info/top_level.txt