Metadata-Version: 2.1
Name: kegg-pull
Version: 3.1.0
Summary: Pulls any and all entries from any and all KEGG databases, pulls KEGG entry IDs, and wraps all the KEGG REST API operations in both Python API and the command line.
Home-page: https://github.com/MoseleyBioinformaticsLab/KEGGpull
Author: Erik Huckvale
Author-email: edhu227@g.uky.edu
License: UNKNOWN
Platform: UNKNOWN
License-File: LICENSE
